{
"type": "FeatureCollection",
"name": "RF_annual_MWS_004_1",
"crs": { "type": "name", "properties": { "name": "urn:ogc:def:crs:OGC:1.3:CRS84" } },
"features": [
{ "type": "Feature", "properties": { "station_na": "kundasale farm", "longitude": 80.68, "latitude": 7.27, "Jan": 81.61904762, "Feb": 52.66666667, "March": 84.47619048, "April": 164.952381, "May": 91.71428571, "June": 66.76190476, "July": 49.38095238, "August": 65.95238095000001, "Sep": 68.57142857, "Oct": 199.6666667, "Nov": 225.5714286, "Dec": 191.8571429, "sum": 1343.190476 }, "geometry": { "type": "Point", "coordinates": [ 80.680000017008098, 7.270000005107587 ] } }
]
}
