{
"type": "FeatureCollection",
"name": "Temperature",
"crs": { "type": "name", "properties": { "name": "urn:ogc:def:crs:OGC:1.3:CRS84" } },
"features": [
{ "type": "Feature", "properties": { "Station": "MR 1", "N": 7.322361111, "E": 80.6175, "T_02032020": 25.7, "T_25032021": 21.9, "T_31012023": 23.1, "T_19042023": 8.1, "T_20062023": 25.1, "T_18092023": 25.1, "T_30012024": 24.6, "T_25032024": 28.1 }, "geometry": { "type": "Point", "coordinates": [ 80.6175, 7.322361111 ] } },
{ "type": "Feature", "properties": { "Station": "MR 2", "N": 7.271972222, "E": 80.60466667, "T_02032020": 24.8, "T_25032021": 21.6, "T_31012023": 22.5, "T_19042023": 27.6, "T_20062023": 24.6, "T_18092023": 24.8, "T_30012024": 24.0, "T_25032024": 27.0 }, "geometry": { "type": "Point", "coordinates": [ 80.60466667, 7.271972222 ] } },
{ "type": "Feature", "properties": { "Station": "MR 3", "N": 7.264166667, "E": 80.59363889, "T_02032020": 24.9, "T_25032021": 22.6, "T_31012023": 22.2, "T_19042023": 27.6, "T_20062023": 24.3, "T_18092023": 24.9, "T_30012024": 23.6, "T_25032024": 26.8 }, "geometry": { "type": "Point", "coordinates": [ 80.59363889, 7.264166667 ] } },
{ "type": "Feature", "properties": { "Station": "MR 4", "N": 7.162472222, "E": 80.57322222000001, "T_02032020": 24.4, "T_25032021": 23.9, "T_31012023": 22.4, "T_19042023": 26.8, "T_20062023": 24.5, "T_18092023": 24.3, "T_30012024": 24.5, "T_25032024": 25.1 }, "geometry": { "type": "Point", "coordinates": [ 80.57322222, 7.162472222 ] } },
{ "type": "Feature", "properties": { "Station": "MR 5", "N": 7.061305556, "E": 80.5385, "T_02032020": 26.8, "T_25032021": 23.2, "T_31012023": 23.8, "T_19042023": 26.4, "T_20062023": 24.1, "T_18092023": 24.0, "T_30012024": 25.2, "T_25032024": 27.0 }, "geometry": { "type": "Point", "coordinates": [ 80.5385, 7.061305556 ] } },
{ "type": "Feature", "properties": { "Station": "MR 6", "N": 7.000522222, "E": 80.49086389, "T_02032020": 25.4, "T_25032021": 23.9, "T_31012023": 22.4, "T_19042023": 25.1, "T_20062023": 23.5, "T_18092023": 23.0, "T_30012024": 24.6, "T_25032024": 26.3 }, "geometry": { "type": "Point", "coordinates": [ 80.49086389, 7.000522222 ] } },
{ "type": "Feature", "properties": { "Station": "MR 7", "N": 6.944441667, "E": 80.54128611, "T_02032020": 24.3, "T_25032021": 23.7, "T_31012023": 21.6, "T_19042023": 24.4, "T_20062023": 22.9, "T_18092023": 22.2, "T_30012024": 23.5, "T_25032024": 25.3 }, "geometry": { "type": "Point", "coordinates": [ 80.54128611, 6.944441667 ] } },
{ "type": "Feature", "properties": { "Station": "MR 8", "N": 6.902986111, "E": 80.58321389, "T_02032020": 23.2, "T_25032021": 25.1, "T_31012023": 21.1, "T_19042023": 24.9, "T_20062023": 23.2, "T_18092023": 22.3, "T_30012024": 23.3, "T_25032024": 25.0 }, "geometry": { "type": "Point", "coordinates": [ 80.58321389, 6.902986111 ] } }
]
}
