{
"type": "FeatureCollection",
"name": "TR_Transport_Pt_MWS_012",
"crs": { "type": "name", "properties": { "name": "urn:ogc:def:crs:OGC:1.3:CRS84" } },
"features": [
{ "type": "Feature", "properties": { "TP_Tp_Tran": 2, "TP_Nm_Tran": "26", "TP_Lb_meth": "8", "TP_GFCODE": "KLMPP" }, "geometry": { "type": "Point", "coordinates": [ 80.770513822076353, 7.180209627582645, 0.0 ] } },
{ "type": "Feature", "properties": { "TP_Tp_Tran": 2, "TP_Nm_Tran": "24", "TP_Lb_meth": "8", "TP_GFCODE": "KLMPP" }, "geometry": { "type": "Point", "coordinates": [ 80.764856696308968, 7.187377104224979, 0.0 ] } },
{ "type": "Feature", "properties": { "TP_Tp_Tran": 2, "TP_Nm_Tran": "25", "TP_Lb_meth": "8", "TP_GFCODE": "KLMPP" }, "geometry": { "type": "Point", "coordinates": [ 80.765238567889995, 7.183385865713198, 0.0 ] } }
]
}
