{
"type": "FeatureCollection",
"name": "TR_Transport_Pt_MWS_011",
"crs": { "type": "name", "properties": { "name": "urn:ogc:def:crs:OGC:1.3:CRS84" } },
"features": [
{ "type": "Feature", "properties": { "TP_Tp_Tran": 2, "TP_Nm_Tran": "47", "TP_Lb_meth": "8", "TP_GFCODE": "KLMPP" }, "geometry": { "type": "Point", "coordinates": [ 80.7682828180249, 7.113412764220339, 0.0 ] } }
]
}
