{
"type": "FeatureCollection",
"name": "MWS0060619",
"crs": { "type": "name", "properties": { "name": "urn:ogc:def:crs:OGC:1.3:CRS84" } },
"features": [
{ "type": "Feature", "properties": { "No": 1, "GND No.": 998, "Scheme": "Bawlanawatta Janapadaya Water tank", "Problem to be addressed/Recommendation": "Tank is dilapidated and leakages are occurring from the tank and probable Water pollution. (60 families) Recommend 1. To construct ferro cement tank of 35 m3 capacity. 2.Fencing and make dense planting of mixed vegetation comprising Agave/Areca nut trees /Kithul/Kumbuk/Mee/ Godapara/Kaduru/Aththikka/Wal del/Kekuna randomly mixed seedlings at 500 mm grid interval.4. Apply mulching, organic manure and NPK fertilizer. Covered area 200 m2.3. Awareness and training on cattle shed management and producing organic fertilizer.", "N": 7.186227, "E": 80.70432, "Estimated Cost": "463,400" }, "geometry": { "type": "Point", "coordinates": [ 80.70432, 7.186227 ] } },
{ "type": "Feature", "properties": { "No": 2, "GND No.": 1035, "Scheme": "Rainwater harvesting tank", "Problem to be addressed/Recommendation": "Public interest on RWH systems. Recommend to provide 50% financial assistance to 15 families to build their own rain water harvesting tanks.", "N": 7.186227, "E": 80.70432, "Estimated Cost": "975,000" }, "geometry": { "type": "Point", "coordinates": [ 80.70432, 7.186227 ] } }
]
}
