{
"type": "FeatureCollection",
"name": "MWS_008_1_Table_6_3",
"crs": { "type": "name", "properties": { "name": "urn:ogc:def:crs:OGC:1.3:CRS84" } },
"features": [
{ "type": "Feature", "properties": { "ID": 1, "N": 7.214485, "E": 80.759116, "Tank name": "Millapokuna Tank", "Land ownership": "DAD", "Remarks": "Recommended to desilt the tank and improve reservation" }, "geometry": { "type": "Point", "coordinates": [ 80.759116, 7.214485 ] } }
]
}
