{
"type": "FeatureCollection",
"name": "MWS_005_Table_6_3",
"crs": { "type": "name", "properties": { "name": "urn:ogc:def:crs:OGC:1.3:CRS84" } },
"features": [
{ "type": "Feature", "properties": { "ID": 1, "N": 7.213453, "E": 80.696547, "Tank name": "Muthukeliyawa Wewa", "Ownership": "DAD", "Remarks": "Recommended to improve reservation" }, "geometry": { "type": "Point", "coordinates": [ 80.696547, 7.213453 ] } },
{ "type": "Feature", "properties": { "ID": 3, "N": 7.22313, "E": 80.67952, "Tank name": "Pihibiyakele  Wewa", "Ownership": "DAD", "Remarks": "Recommended to improve reservation" }, "geometry": { "type": "Point", "coordinates": [ 80.67952, 7.22313 ] } },
{ "type": "Feature", "properties": { "ID": 4, "N": 7.22105, "E": 80.68088, "Tank name": "Katukithula Wewa", "Ownership": "DAD", "Remarks": "Recommended to improve reservation " }, "geometry": { "type": "Point", "coordinates": [ 80.68088, 7.22105 ] } },
{ "type": "Feature", "properties": { "ID": 5, "N": 7.2027805, "E": 80.69781, "Tank name": "Bogamuwa Wewa", "Ownership": "DAD", "Remarks": "Recommended to improve reservation " }, "geometry": { "type": "Point", "coordinates": [ 80.69781, 7.2027805 ] } }
]
}
