{
"type": "FeatureCollection",
"name": "RF_april_MWS_021_1",
"crs": { "type": "name", "properties": { "name": "urn:ogc:def:crs:OGC:1.3:CRS84" } },
"features": [
{ "type": "Feature", "properties": { "station_na": "high forest estate", "longitude": 80.84, "latitude": 7.06, "year_1976": 1, "year_1977": 30, "year_1978": 2, "year_1979": 82, "year_1980": 2, "year_1981": 33, "year_1982": 34, "year_1983": 17, "year_1984": 9, "year_1985": 115, "year_1986": 44, "year_1987": 57, "year_1988": 24, "year_1989": 139, "year_1990": 87, "year_1991": 86, "year_1992": 34, "year_1993": 161, "year_1994": 24, "year_1995": 44, "year_1996": 312, "year_1997": 158, "year_1998": 129, "year_1999": 111, "year_2000": 109, "year_2001": 66, "year_2002": 32, "year_2003": 78, "year_2004": 52, "year_2005": 18, "year_2006": 98, "year_2007": 159, "year_2008": 24, "year_2009": 13, "year_2010": 121, "year_2011": 17, "year_2012": 0, "year_2013": 238, "year_2014": 29, "year_2015": 49, "year_2016": 56, "year_2017": 42, "year_2018": 58, "year_2019": 43, "year_2020": 144, "AVG": 68.85714286 }, "geometry": { "type": "Point", "coordinates": [ 80.840000016676342, 7.060000005295482 ] } }
]
}
