{
"type": "FeatureCollection",
"name": "RF_february_MWS_002_1",
"crs": { "type": "name", "properties": { "name": "urn:ogc:def:crs:OGC:1.3:CRS84" } },
"features": [
{ "type": "Feature", "properties": { "station_na": "loolecondera estate", "longitude": 80.7, "latitude": 7.12, "year_1976": 14.0, "year_1977": 21.0, "year_1978": 58.0, "year_1979": 0, "year_1980": 0, "year_1981": 69.0, "year_1982": 0, "year_1983": 0, "year_1984": 426.0, "year_1985": 169.0, "year_1986": 285.0, "year_1987": 32, "year_1988": 185.0, "year_1989": 22.0, "year_1990": 217.0, "year_1991": 25.0, "year_1992": 0, "year_1993": 17.0, "year_1994": 220.0, "year_1995": 121.0, "year_1996": 180.0, "year_1997": 36.0, "year_1998": 59.0, "year_1999": 147.0, "year_2000": 495.0, "year_2001": 91.0, "year_2002": 106.0, "year_2003": 94.0, "year_2004": 96.0, "year_2005": 64.0, "year_2006": 155.0, "year_2007": 6.0, "year_2008": 174.0, "year_2009": 0.0, "year_2010": 12, "year_2011": 347.0, "year_2012": 134.0, "year_2013": 151.0, "year_2014": 28.0, "year_2015": 275.0, "year_2016": 78.0, "year_2017": 170.0, "year_2018": 58.0, "year_2019": 116.0, "year_2020": 130.0, "AVG": 132.3809524 }, "geometry": { "type": "Point", "coordinates": [ 80.700000016976162, 7.120000005256173 ] } },
{ "type": "Feature", "properties": { "station_na": "loolecondera_est", "longitude": 80.711, "latitude": 7.128, "year_1976": 14.0, "year_1977": 21.0, "year_1978": 58.0, "year_1979": 0, "year_1980": 0, "year_1981": 69.0, "year_1982": 0, "year_1983": 0, "year_1984": 426.0, "year_1985": 169.0, "year_1986": 285.0, "year_1987": 32, "year_1988": 185.0, "year_1989": 22.0, "year_1990": 217.0, "year_1991": 25.0, "year_1992": 0, "year_1993": 17.0, "year_1994": 220.0, "year_1995": 121.0, "year_1996": 180.0, "year_1997": 36.0, "year_1998": 59.0, "year_1999": 147.0, "year_2000": 495.0, "year_2001": 91.0, "year_2002": 106.0, "year_2003": 94.0, "year_2004": 96.0, "year_2005": 64.0, "year_2006": 155.0, "year_2007": 6.0, "year_2008": 174.0, "year_2009": 0.0, "year_2010": 12, "year_2011": 347.0, "year_2012": 134.0, "year_2013": 151.0, "year_2014": 28.0, "year_2015": 275.0, "year_2016": 78.0, "year_2017": 170.0, "year_2018": 58.0, "year_2019": 116.0, "year_2020": 130.0, "AVG": 132.3809524 }, "geometry": { "type": "Point", "coordinates": [ 80.711000016951502, 7.128000005246367 ] } }
]
}
